ApacheShiro12XReferenceManualZhongwenfanyi/README.md
ApacheShiro12XReferenceManualZhongwenfanyi/__init__.py
ApacheShiro12XReferenceManualZhongwenfanyi/__main__.py
ApacheShiro12XReferenceManualZhongwenfanyi/file.epub
ApacheShiro12XReferenceManualZhongwenfanyi/index.html
ApacheShiro12XReferenceManualZhongwenfanyi/css/__init__.py
ApacheShiro12XReferenceManualZhongwenfanyi/css/annotations.css
ApacheShiro12XReferenceManualZhongwenfanyi/css/main.css
ApacheShiro12XReferenceManualZhongwenfanyi/css/normalize.css
ApacheShiro12XReferenceManualZhongwenfanyi/css/popup.css
ApacheShiro12XReferenceManualZhongwenfanyi/font/__init__.py
ApacheShiro12XReferenceManualZhongwenfanyi/font/fontello.eot
ApacheShiro12XReferenceManualZhongwenfanyi/font/fontello.svg
ApacheShiro12XReferenceManualZhongwenfanyi/font/fontello.ttf
ApacheShiro12XReferenceManualZhongwenfanyi/font/fontello.woff
ApacheShiro12XReferenceManualZhongwenfanyi/img/__init__.py
ApacheShiro12XReferenceManualZhongwenfanyi/img/annotator-glyph-sprite.png
ApacheShiro12XReferenceManualZhongwenfanyi/img/annotator-icon-sprite.png
ApacheShiro12XReferenceManualZhongwenfanyi/img/apple-touch-icon.png
ApacheShiro12XReferenceManualZhongwenfanyi/img/cancelfullscreen.png
ApacheShiro12XReferenceManualZhongwenfanyi/img/close.png
ApacheShiro12XReferenceManualZhongwenfanyi/img/fullscreen.png
ApacheShiro12XReferenceManualZhongwenfanyi/img/loader.gif
ApacheShiro12XReferenceManualZhongwenfanyi/img/menu-icon.png
ApacheShiro12XReferenceManualZhongwenfanyi/img/save.png
ApacheShiro12XReferenceManualZhongwenfanyi/img/saved.png
ApacheShiro12XReferenceManualZhongwenfanyi/img/settings-s.png
ApacheShiro12XReferenceManualZhongwenfanyi/img/settings.png
ApacheShiro12XReferenceManualZhongwenfanyi/img/star.png
ApacheShiro12XReferenceManualZhongwenfanyi/js/__init__.py
ApacheShiro12XReferenceManualZhongwenfanyi/js/epub.js
ApacheShiro12XReferenceManualZhongwenfanyi/js/epub.min.js
ApacheShiro12XReferenceManualZhongwenfanyi/js/epub.min.map
apache_shiro_1_2_x_reference_manual_zhongwenfanyi-2024.2.29.0.dist-info/METADATA
apache_shiro_1_2_x_reference_manual_zhongwenfanyi-2024.2.29.0.dist-info/WHEEL
apache_shiro_1_2_x_reference_manual_zhongwenfanyi-2024.2.29.0.dist-info/entry_points.txt
apache_shiro_1_2_x_reference_manual_zhongwenfanyi-2024.2.29.0.dist-info/top_level.txt
apache_shiro_1_2_x_reference_manual_zhongwenfanyi-2024.2.29.0.dist-info/RECORD
